{
  "pages.unsupported-platform.title": "pages.unsupported-platform.title",
  "pages.unsupported-platform.description": "pages.unsupported-platform.description",
  "pages.unsupported-platform.progress": "pages.unsupported-platform.progress",
  "pages.unsupported-platform.here": "pages.unsupported-platform.here",
  "pages.register.title": "pages.register.title",
  "pages.register.subtitle": "pages.register.subtitle",
  "pages.register.already-account": "pages.register.already-account",
  "pages.register.sign-in": "pages.register.sign-in",
  "pages.login.title": "pages.login.title",
  "pages.login.subtitle": "pages.login.subtitle",
  "pages.login.no-account": "pages.login.no-account",
  "pages.login.register": "pages.login.register",
  "pages.forgot-password.title": "pages.forgot-password.title",
  "pages.forgot-password.subtitle": "pages.forgot-password.subtitle",
  "pages.forgot-password.connection-page": "pages.forgot-password.connection-page",
  "components.ui.header.settings-account": "components.ui.header.settings-account",
  "components.ui.header.greenhouse-settings": "components.ui.header.greenhouse-settings",
  "components.ui.header.greenhouse-create": "components.ui.header.greenhouse-create",
  "components.ui.header.settings": "components.ui.header.settings",
  "components.ui.fields.name": "components.ui.fields.name",
  "components.ui.fields.sourceAddress": "components.ui.fields.sourceAddress",
  "components.ui.button.submit": "components.ui.button.submit",
  "components.greenhouse-form.step.details": "components.greenhouse-form.step.details",
  "components.greenhouse-form.step.crops": "components.greenhouse-form.step.crops",
  "components.greenhouse-form.step.sensors": "components.greenhouse-form.step.sensors",
  "components.greenhouse-form.step.review": "components.greenhouse-form.step.review",
  "components.greenhouse-form.label.name": "components.greenhouse-form.label.name",
  "components.ui.button.next": "components.ui.button.next",
  "components.ui.button.return": "components.ui.button.return",
  "components.crops.crop-selector.noItemsAvailable": "components.crops.crop-selector.noItemsAvailable",
  "components.ui.fields.scientificName": "components.ui.fields.scientificName",
  "components.ui.fields.commonName": "components.ui.fields.commonName",
  "components.ui.fields.enterQuantity": "components.ui.fields.enterQuantity",
  "components.crops.crop-selector.selectCrop": "components.crops.crop-selector.selectCrop",
  "components.ui.fields.plantingDate": "components.ui.fields.plantingDate",
  "components.ui.fields.quantity": "components.ui.fields.quantity",
  "components.ui.button.add": "components.ui.button.add",
  "shared.nickname.label": "shared.nickname.label",
  "shared.nickname.placeholder": "shared.nickname.placeholder",
  "shared.email.label": "shared.email.label",
  "shared.email.placeholder": "shared.email.placeholder",
  "shared.password.label": "shared.password.label",
  "shared.password.confirm": "shared.password.confirm",
  "shared.buttons.register": "shared.buttons.register",
  "shared.password.forgot": "shared.password.forgot",
  "shared.buttons.connection": "shared.buttons.connection",
  "shared.buttons.send": "shared.buttons.send",
  "shared.errors.http.0": "shared.errors.http.0",
  "shared.errors.http.400": "shared.errors.http.400",
  "shared.errors.http.401": "shared.errors.http.401",
  "shared.errors.http.403": "shared.errors.http.403",
  "shared.errors.http.404": "shared.errors.http.404",
  "shared.errors.http.409": "shared.errors.http.409",
  "shared.errors.http.422": "shared.errors.http.422",
  "shared.errors.http.500": "shared.errors.http.500",
  "components.ui.header.new-greenhouse": "components.ui.header.new-greenhouse",
  "components.sensors.sensor-form.dialog.title": "components.sensors.sensor-form.dialog.title",
  "components.greenhouse-form.alert.create": "components.greenhouse-form.alert.create",
  "components.ui.alert.info": "components.ui.alert.info",
  "components.ui.alert.form-invalid": "components.ui.alert.form-invalid",
  "components.ui.alert.error": "components.ui.alert.error",
  "components.greenhouses-form.label.name": "components.greenhouses-form.label.name",
  "components.greenhouses-form.label.location": "components.greenhouses-form.label.location",
  "components.greenhouses-form.label.crops": "components.greenhouses-form.label.crops",
  "components.greenhouses-form.label.sensors": "components.greenhouses-form.label.sensors",
  "components.greenhouses-form.alert.remove-sensor": "components.greenhouses-form.alert.remove-sensor",
  "components.greenhouses-form.alert.duplicate-sensor": "components.greenhouses-form.alert.duplicate-sensor",
  "components.ui.alert.warning": "components.ui.alert.warning",
  "components.greenhouses-form.alert.sensor-updated": "components.greenhouses-form.alert.sensor-updated",
  "components.ui.alert.success": "components.ui.alert.success",
  "components.greenhouses-form.alert.sensor-added": "components.greenhouses-form.alert.sensor-added",
  "components.greenhouses-form.sensor": "components.greenhouses-form.sensor",
  "components.crops.crop-selector.dialogLabel": "components.crops.crop-selector.dialogLabel",
  "shared.alerts.errorCreds": "shared.alerts.errorCreds",
  "shared.alerts.error": "shared.alerts.error"
}
